insa_its/__init__.py
insa_its/config.py
insa_its/dashboard.py
insa_its/detector.py
insa_its/embeddings.py
insa_its/exceptions.py
insa_its/hallucination.py
insa_its/license.py
insa_its/local_llm.py
insa_its/monitor.py
insa_its/integrations/__init__.py
insa_its/integrations/crewai.py
insa_its/integrations/exports.py
insa_its/integrations/langchain.py
insa_its/integrations/langgraph.py
insa_its/integrations/slack.py
insa_its/premium/__init__.py
insa_its/premium/_license_header.py
insa_its/premium/adaptive_dict.py
insa_its/premium/advanced_detector.py
insa_its/premium/anchor_forensics.py
insa_its/premium/decipher_engine.py
insa_its-2.4.0.dist-info/licenses/LICENSE
insa_its-2.4.0.dist-info/licenses/LICENSE.premium
tests/__init__.py
tests/test_graceful_degradation.py
tests/test_hallucination.py
tests/test_insaits.py
tests/test_integrations.py
tests/test_open_core.py
tests/test_v2_features.py
insa_its-2.4.0.dist-info/METADATA
insa_its-2.4.0.dist-info/WHEEL
insa_its-2.4.0.dist-info/top_level.txt
insa_its-2.4.0.dist-info/RECORD
