Metadata-Version: 2.4
Name: insa-its
Version: 2.4.0
Summary: Open-core multi-LLM communication monitoring, hallucination detection & deciphering for agent systems
Home-page: https://github.com/Nomadu27/InsAIts
Author: YuyAI / InsAIts Team
Author-email: info@yuyai.pro
Classifier: Development Status :: 5 - Production/Stable
Classifier: Intended Audience :: Developers
Classifier: License :: OSI Approved :: Apache Software License
Classifier: Programming Language :: Python :: 3.8
Classifier: Programming Language :: Python :: 3.9
Classifier: Programming Language :: Python :: 3.10
Classifier: Programming Language :: Python :: 3.11
Classifier: Programming Language :: Python :: 3.12
Classifier: Programming Language :: Python :: 3.13
Requires-Python: >=3.8
License-File: LICENSE
License-File: LICENSE.premium
Requires-Dist: numpy>=1.20.0
Requires-Dist: requests>=2.26.0
Requires-Dist: websocket-client>=1.0.0
Provides-Extra: local
Requires-Dist: sentence-transformers>=2.2.0; extra == "local"
Provides-Extra: graph
Requires-Dist: networkx>=2.6.0; extra == "graph"
Provides-Extra: full
Requires-Dist: sentence-transformers>=2.2.0; extra == "full"
Requires-Dist: networkx>=2.6.0; extra == "full"
Dynamic: author
Dynamic: author-email
Dynamic: classifier
Dynamic: description
Dynamic: description-content-type
Dynamic: home-page
Dynamic: license-file
Dynamic: provides-extra
Dynamic: requires-dist
Dynamic: requires-python
Dynamic: summary
